kanonym4text/__init__.py
kanonym4text/data/5000_most_common_words_by_order.txt
kanonym4text/objects/__init__.py
kanonym4text/objects/kanonym.py
kanonym4text/utils/__init__.py
kanonym4text/utils/anonym_utils.py
kanonym4text/utils/cluster_utils.py
kanonym4text/utils/llm_utils.py
kanonym4text/utils/models.py
kanonym4text/utils/nlp_utils.py
kanonym4text/utils/utilization_utils.py
kanonym4text-0.2.7.dist-info/LICENSE
kanonym4text-0.2.7.dist-info/METADATA
kanonym4text-0.2.7.dist-info/WHEEL
kanonym4text-0.2.7.dist-info/top_level.txt
kanonym4text-0.2.7.dist-info/RECORD
